<metadata xml:lang="en"><Esri><CreaDate>20190313</CreaDate><CreaTime>11573100</CreaTime><ArcGISFormat>1.0</ArcGISFormat><SyncOnce>FALSE</SyncOnce><DataProperties><itemProps><itemName Sync="TRUE">Noyyal_Basin_Boundary</itemName><imsContentType Sync="TRUE">002</imsContentType><nativeExtBox><westBL Sync="TRUE">24700.663645</westBL><eastBL Sync="TRUE">166666.732245</eastBL><southBL Sync="TRUE">1207778.139939</southBL><northBL Sync="TRUE">1255388.711739</northBL><exTypeCode Sync="TRUE">1</exTypeCode></nativeExtBox><itemSize Sync="TRUE">0.171</itemSize><itemLocation><linkage Sync="TRUE">file://\\LAPTOP-AEUJ9TRO\G$\ATREE\Data\Noyyal_Bhavani_Basins\Noyyal_Bhavani_Basind_Shapefiles\Creative_Commons_License\Noyyal_Basin_Boundary.shp</linkage><protocol Sync="TRUE">Local Area Network</protocol></itemLocation></itemProps><coordRef><type Sync="TRUE">Projected</type><geogcsn Sync="TRUE">GCS_WGS_1984</geogcsn><csUnits Sync="TRUE">Linear Unit: Meter (1.000000)</csUnits><projcsn Sync="TRUE">WGS_1984_UTM_Zone_44N</projcsn><peXml Sync="TRUE">&lt;ProjectedCoordinateSystem xsi:type='typens:ProjectedCoordinateSystem' xmlns:xsi='http://www.w3.org/2001/XMLSchema-instance' xmlns:xs='http://www.w3.org/2001/XMLSchema' xmlns:typens='http://www.esri.com/schemas/ArcGIS/10.4'&gt;&lt;WKT&gt;PROJCS[&amp;quot;WGS_1984_UTM_Zone_44N&amp;quot;,GEOGCS[&amp;quot;GCS_WGS_1984&amp;quot;,DATUM[&amp;quot;D_WGS_1984&amp;quot;,SPHEROID[&amp;quot;WGS_1984&amp;quot;,6378137.0,298.257223563]],PRIMEM[&amp;quot;Greenwich&amp;quot;,0.0],UNIT[&amp;quot;Degree&amp;quot;,0.0174532925199433]],PROJECTION[&amp;quot;Transverse_Mercator&amp;quot;],PARAMETER[&amp;quot;False_Easting&amp;quot;,500000.0],PARAMETER[&amp;quot;False_Northing&amp;quot;,0.0],PARAMETER[&amp;quot;Central_Meridian&amp;quot;,81.0],PARAMETER[&amp;quot;Scale_Factor&amp;quot;,0.9996],PARAMETER[&amp;quot;Latitude_Of_Origin&amp;quot;,0.0],UNIT[&amp;quot;Meter&amp;quot;,1.0],AUTHORITY[&amp;quot;EPSG&amp;quot;,32644]]&lt;/WKT&gt;&lt;XOrigin&gt;-5120900&lt;/XOrigin&gt;&lt;YOrigin&gt;-9998100&lt;/YOrigin&gt;&lt;XYScale&gt;450445547.3910538&lt;/XYScale&gt;&lt;ZOrigin&gt;-100000&lt;/ZOrigin&gt;&lt;ZScale&gt;10000&lt;/ZScale&gt;&lt;MOrigin&gt;-100000&lt;/MOrigin&gt;&lt;MScale&gt;10000&lt;/MScale&gt;&lt;XYTolerance&gt;0.001&lt;/XYTolerance&gt;&lt;ZTolerance&gt;0.001&lt;/ZTolerance&gt;&lt;MTolerance&gt;0.001&lt;/MTolerance&gt;&lt;HighPrecision&gt;true&lt;/HighPrecision&gt;&lt;WKID&gt;32644&lt;/WKID&gt;&lt;LatestWKID&gt;32644&lt;/LatestWKID&gt;&lt;/ProjectedCoordinateSystem&gt;</peXml></coordRef></DataProperties><SyncDate>20190313</SyncDate><SyncTime>11573200</SyncTime><ModDate>20190313</ModDate><ModTime>11580700</ModTime><scaleRange><minScale>150000000</minScale><maxScale>5000</maxScale></scaleRange><ArcGISProfile>ItemDescription</ArcGISProfile></Esri><dataIdInfo><envirDesc Sync="TRUE"> Version 6.2 (Build 9200) ; Esri ArcGIS 10.4.0.5524</envirDesc><dataLang><languageCode value="eng" Sync="TRUE"/><countryCode value="USA" Sync="TRUE"/></dataLang><idCitation><resTitle Sync="TRUE">Noyyal_Basin_Boundary</resTitle><presForm><PresFormCd value="005" Sync="TRUE"/></presForm></idCitation><spatRpType><SpatRepTypCd value="001" Sync="TRUE"/></spatRpType><dataExt><geoEle xmlns=""><GeoBndBox esriExtentType="search"><exTypeCode Sync="TRUE">1</exTypeCode><westBL Sync="TRUE">76.648250</westBL><eastBL Sync="TRUE">77.950984</eastBL><northBL Sync="TRUE">11.340606</northBL><southBL Sync="TRUE">10.894973</southBL></GeoBndBox></geoEle></dataExt><idCredit>Contextual Water Targets Pilot Study in the Noyyal-Bhavani River Basin by Ashoka Trust for Research in Ecology and the Environment (ATREE), Bangalore, India. is licensed under a Creative Commons Attribution-NonCommercial-ShareAlike 4.0 International License. If it is reused please give appropriate credit,provide a link to the license, and indicate if changes were made.
</idCredit><resConst><Consts><useLimit>&lt;DIV STYLE="text-align:Left;"&gt;&lt;DIV&gt;&lt;P&gt;&lt;SPAN&gt;This work is licensed under the Creative Commons Attribution-NonCommercial-ShareAlike 4.0 International License. To view a copy of this license, visit http://creativecommons.org/licenses/by-nc-sa/4.0/.&lt;/SPAN&gt;&lt;/P&gt;&lt;/DIV&gt;&lt;/DIV&gt;</useLimit></Consts></resConst></dataIdInfo><mdLang><languageCode value="eng" Sync="TRUE"/><countryCode value="USA" Sync="TRUE"/></mdLang><mdChar><CharSetCd value="004" Sync="TRUE"/></mdChar><distInfo><distFormat><formatName Sync="TRUE">Shapefile</formatName></distFormat><distTranOps><transSize Sync="TRUE">0.171</transSize></distTranOps></distInfo><mdHrLv><ScopeCd value="005" Sync="TRUE"/></mdHrLv><mdHrLvName Sync="TRUE">dataset</mdHrLvName><refSysInfo><RefSystem><refSysID><identCode code="32644" Sync="TRUE"/><idCodeSpace Sync="TRUE">EPSG</idCodeSpace><idVersion Sync="TRUE">2.1(3.0.1)</idVersion></refSysID></RefSystem></refSysInfo><spatRepInfo><VectSpatRep><geometObjs Name="Noyyal_Basin_Boundary"><geoObjTyp><GeoObjTypCd value="002" Sync="TRUE"/></geoObjTyp><geoObjCnt Sync="TRUE">1</geoObjCnt></geometObjs><topLvl><TopoLevCd value="001" Sync="TRUE"/></topLvl></VectSpatRep></spatRepInfo><spdoinfo><ptvctinf><esriterm Name="Noyyal_Basin_Boundary"><efeatyp Sync="TRUE">Simple</efeatyp><efeageom code="4" Sync="TRUE"/><esritopo Sync="TRUE">FALSE</esritopo><efeacnt Sync="TRUE">1</efeacnt><spindex Sync="TRUE">TRUE</spindex><linrefer Sync="TRUE">FALSE</linrefer></esriterm></ptvctinf></spdoinfo><eainfo><detailed Name="Noyyal_Basin_Boundary"><enttyp><enttypl Sync="TRUE">Noyyal_Basin_Boundary</enttypl><enttypt Sync="TRUE">Feature Class</enttypt><enttypc Sync="TRUE">1</enttypc></enttyp><attr><attrlabl Sync="TRUE">FID</attrlabl><attalias Sync="TRUE">FID</attalias><attrtype Sync="TRUE">OID</attrtype><attwidth Sync="TRUE">4</attwidth><atprecis Sync="TRUE">0</atprecis><attscale Sync="TRUE">0</attscale><attrdef Sync="TRUE">Internal feature number.</attrdef><attrdefs Sync="TRUE">Esri</attrdefs><attrdomv><udom Sync="TRUE">Sequential unique whole numbers that are automatically generated.</udom></attrdomv></attr><attr><attrlabl Sync="TRUE">Shape</attrlabl><attalias Sync="TRUE">Shape</attalias><attrtype Sync="TRUE">Geometry</attrtype><attwidth Sync="TRUE">0</attwidth><atprecis Sync="TRUE">0</atprecis><attscale Sync="TRUE">0</attscale><attrdef Sync="TRUE">Feature geometry.</attrdef><attrdefs Sync="TRUE">Esri</attrdefs><attrdomv><udom Sync="TRUE">Coordinates defining the features.</udom></attrdomv></attr><attr><attrlabl Sync="TRUE">ID</attrlabl><attalias Sync="TRUE">ID</attalias><attrtype Sync="TRUE">Double</attrtype><attwidth Sync="TRUE">19</attwidth><atprecis Sync="TRUE">0</atprecis><attscale Sync="TRUE">0</attscale></attr><attr><attrlabl Sync="TRUE">Basin</attrlabl><attalias Sync="TRUE">Basin</attalias><attrtype Sync="TRUE">String</attrtype><attwidth Sync="TRUE">50</attwidth><atprecis Sync="TRUE">0</atprecis><attscale Sync="TRUE">0</attscale></attr></detailed></eainfo><mdDateSt Sync="TRUE">20190313</mdDateSt><Binary><Thumbnail><Data EsriPropertyType="PictureX">/9j/4AAQSkZJRgABAQEBLAEsAAD/2wBDAAMCAgMCAgMDAwMEAwMEBQgFBQQEBQoHBwYIDAoMDAsK
CwsNDhIQDQ4RDgsLEBYQERMUFRUVDA8XGBYUGBIUFRT/2wBDAQMEBAUEBQkFBQkUDQsNFBQUFBQU
FBQUFBQUFBQUFBQUFBQUFBQUFBQUFBQUFBQUFBQUFBQUFBQUFBQUFBQUFBT/wAARCACNAZMDASIA
AhEBAxEB/8QAHwAAAQUBAQEBAQEAAAAAAAAAAAECAwQFBgcICQoL/8QAtRAAAgEDAwIEAwUFBAQA
AAF9AQIDAAQRBRIhMUEGE1FhByJxFDKBkaEII0KxwRVS0fAkM2JyggkKFhcYGRolJicoKSo0NTY3
ODk6Q0RFRkdISUpTVFVWV1hZWmNkZWZnaGlqc3R1dnd4eXqDhIWGh4iJipKTlJWWl5iZmqKjpKWm
p6ipqrKztLW2t7i5usLDxMXGx8jJytLT1NXW19jZ2uHi4+Tl5ufo6erx8vP09fb3+Pn6/8QAHwEA
AwEBAQEBAQEBAQAAAAAAAAECAwQFBgcICQoL/8QAtREAAgECBAQDBAcFBAQAAQJ3AAECAxEEBSEx
BhJBUQdhcRMiMoEIFEKRobHBCSMzUvAVYnLRChYkNOEl8RcYGRomJygpKjU2Nzg5OkNERUZHSElK
U1RVVldYWVpjZGVmZ2hpanN0dXZ3eHl6goOEhYaHiImKkpOUlZaXmJmaoqOkpaanqKmqsrO0tba3
uLm6wsPExcbHyMnK0tPU1dbX2Nna4uPk5ebn6Onq8vP09fb3+Pn6/9oADAMBAAIRAxEAPwD570fS
PGv/AAUe+KHivxj4x8V6lpnhSwvpH07SXn+1JpyTY2WtsuEjQLHFEHkCAyFVZgWYkd1/w7Q8Jf8A
Q361/wB+Yf8ACj/gmh/yTvxf/wBhWP8A9EivseobdzJt3Pjj/h2h4S/6G/Wv+/MP+FH/AA7Q8Jf9
DfrX/fmH/Cvseildi5mfHH/DtDwl/wBDfrX/AH5h/wAKP+HaHhL/AKG/Wv8AvzD/AIV9j0UXYczP
jj/h2h4S/wChv1r/AL8w/wCFH/DtDwl/0N+tf9+Yf8K+utZ1zTfDtg99q2oWumWUf37m8mWGNfqz
EAV5Fr/7Znwd8OzvBN4zt7uZe2n201yp+johT9aLsLs8i/4doeEv+hv1r/vzD/hR/wAO0PCX/Q36
1/35h/wrrb7/AIKGfCe1kCxHXLwZxvgsAB9fndT+laWm/t8fB6+x5+s3+nZ/5+dNmOP+/YanqP3j
gP8Ah2h4S/6G/Wv+/MP+FH/DtDwl/wBDfrX/AH5h/wAK+ifBnx9+HXxBkji0HxjpV7cyHCWrTiGd
vpFJtc/lXfUrsV2fHH/DtDwl/wBDfrX/AH5h/wAKP+HaHhL/AKG/Wv8AvzD/AIV9j0UXYczPjj/h
2h4S/wChv1r/AL8w/wCFH/DtDwl/0N+tf9+Yf8K+x6KLsOZnxx/w7Q8Jf9DfrX/fmH/Cj/h2h4S/
6G/Wv+/MP+FfY9FF2HMz44/4doeEv+hv1r/vzD/hR/w7Q8Jf9DfrX/fmH/CvseuZ8ffEzwv8L9I/
tPxTrdro1oeEM7EvIfREGWc+yg0XYczPl7/h2h4S/wChv1r/AL8w/wCFH/DtDwl/0N+tf9+Yf8Ks
+Nf+Ckng7SJWi8NeHNS8RMpwZrmRbKI+6kh2P4qK88vP+CmevyTA2vgfTYYs8rNeySNj6hV/lT1K
947r/h2h4S/6G/Wv+/MP+FH/AA7Q8Jf9DfrX/fmH/Cue0X/gpuDNGmr+ASsJPzzWWp5YD2Rohn/v
oV738NP2yPhf8TrqCxtdbbRtUm4Sx1mP7OzH+6HyYyfQBsn0o1F7x5L/AMO0PCX/AEN+tf8AfmH/
AAo/4doeEv8Aob9a/wC/MP8AhX2PRSuxczPjj/h2h4S/6G/Wv+/MP+FH/DtDwl/0N+tf9+Yf8K+x
6KLsOZnxx/w7Q8Jf9DfrX/fmH/Cj/h2h4S/6G/Wv+/MP+FfY9FF2HMz44/4doeEv+hv1r/vzD/hR
/wAO0PCX/Q361/35h/wr6a+InxY8I/CfTFv/ABXrtrpEL/6uOQlpZf8AcjUFm/AHHevmfxl/wUo8
K6XMYvDPhbUdeCnBnvZ1soz7qAJGI+oWnqP3mN/4doeEv+hv1r/vzD/hR/w7Q8Jf9DfrX/fmH/Cu
Euf+CmXiFpgbfwRpkUOeVkvJHb8wo/lW5of/AAU2ja4jTWfALRwE/PNY6kGYfRGjAP8A30KNR+8b
/wDw7Q8Jf9DfrX/fmH/Cj/h2h4S/6G/Wv+/MP+FewfDH9rz4ZfFS7gsdP1w6Zqs3Cafq8f2eRj/d
VslGb/ZVifavZ6V2Tdnxx/w7Q8Jf9DfrX/fmH/Cj/h2h4S/6G/Wv+/MP+FfY9FF2HMz44/4doeEv
+hv1r/vzD/hR/wAO0PCX/Q361/35h/wr7Hoouw5mfHH/AA7Q8Jf9DfrX/fmH/Cj/AIdoeEv+hv1r
/vzD/hX2PXGfEr4yeDfhFYpdeK9ettL8wZitzmSeX/ciUFiPfGB3Iouw5mfNf/DtDwl/0N+tf9+Y
f8KP+HaHhL/ob9a/78w/4Uzxh/wUs8N6fcGLw14S1DWkBwZ7+5WzU+6gLISPrtrhp/8Agpl4ia4B
h8E6ZHD3SS8kZv8AvoAfyp6le8d5/wAO0PCX/Q361/35h/wo/wCHaHhL/ob9a/78w/4ViaB/wU2t
5LmNNb8BywW/8c+n6iJHH0jeNQf++xX0J8L/ANq74a/Fq6isdI10WerS/c03VIzbzMf7qk/I59lY
mjUXvHi3/DtDwl/0N+tf9+Yf8KP+HaHhL/ob9a/78w/4V9j0UrsXMz44/wCHaHhL/ob9a/78w/4V
z/jn/gn8/wAP/D9x4q8DeNNUj8R6GP7StN6iKTfD+8UxSxkNHICuVYfxAdOo+56x/GX/ACKGuf8A
XjP/AOi2ouw5mfMnwX/4LNeIvhz8L/D/AIa8VeBLjx/rumQtBP4ju/EQt5rxQ7GMun2VyWWMohdm
ZnKF2JZjRX5wUVobH6F/8E0P+Sd+L/8AsKx/+iRX2PXxx/wTQ/5J34v/AOwrH/6JFfY9ZvcxluFF
FUde13T/AAxot7q2q3cdjptnE09xcTHCxooySaRJNqGoWuk2Nxe31zFZ2duhlmuJ3CJGgGSzMeAA
O5r4f+O3/BQ5oZ7jSPhlbowUlH1++i3A+8ER7f7T/wDfPevE/wBpr9rHXPjpqU2l2DSaT4Mhl/cW
Kth7rB+WScjqe4TovHUjNcd+z/8As5eOv2mPGyeGfA+lfbbhVEl1ezkx2llGf+Wk0mDtHXAALNjC
gmrUTVR7nH+L/HfiLx/qbah4j1q91q7YkiS8mZ9ueyg8KPYACo/DHgvxD42u3tfDug6nr90gy0Ol
2cly4HqVRSa/aX9m7/gkr8L/AIU2sOo+PlX4k+JSoLJeIY9Ngb0SDP7z03SEg9dq19reG/C2i+Dt
Li0zQNIsND02L/V2em2yW8KfREAA/KqLP5ztL/Y2+O2sRGS2+EPjMIBnM+izw5HtvUZ/CsXXv2Z/
i94XR31b4W+MtPiQEtLcaDdLGAOp3GPGPxr+l+igD+Vh1aN2VlKupwVYYIPpXsfwm/a0+I3wjlii
stZk1jSFIB0vVmaeHb6ISd0f/ASB6g1++nxX/Zh+FXxuhmXxr4E0XWrmVSpv2thFeLkfw3CbZB+D
V+ZH7VH/AAR/8QeB7XUPEnwg1CbxZo8KtM/h29A/tKJRyRC6gLPgZ+XCvwAN5oA9G+AX7V3hH48Q
rZ27nRfEqpul0e8cFmwOWhfgSKPoGHdQOa9rr8N4J73QdUSWGS40/UbSXKuhaOWGRT1B4KsCPqCK
/Rz9kD9r1fitHF4Q8XTRw+LoY/8ARrw4VdSVRzx0EoAyQOGGSOhFQ0ZSjbY+rKKKKkgKKK8M/a3/
AGgv+FD/AA/RtOMb+J9XLW+nI+CIsD55yO4TK4HdmXtmgZy37U37ZGn/AAdW58NeGfK1TxmVxIzD
dBp+RkF/70mCCE7dW7A/DHg/wJ8VP2sPiA9tothq/jnxHNgzTsSyW6EnBkkYhIY+uMlV7D0ro/2W
f2afFn7YnxhXQ7KaZLTzPtuveIJwZBaQs2WdifvSuchVzlmyTgBiP3z+BfwF8Gfs5+A7Xwn4J0pd
P0+L557h8NcXkuMGaaTGXc/kBgKAAANErGyVj86fhD/wRKeaC2u/ib4/aB2UNLpXhiAFlz2+0zAj
I6cREe5r3rTv+CPX7P8AYwGOZPFGoORjzbjVgGHv8kaj9K+36/CX9qL/AIKNfGbxV8a/ES+GfF+p
eDfDmk6jNZ6dpmlsIf3cTsgeY4y7tjcQ2QM4A4pjPs/xt/wRX+E+rWMo8MeLfFHh3UD9yS7eC+t1
+seyNj/38FfDX7Sn/BMv4t/s92s+sWtonjvwrCpeTVNCiZpbdR1M1ucugxkll3qB1YV+pf8AwTl/
aY1/9qD9n0654qWN/Emj6lLo95eQxiNLwpHFKs20AKrFZVDAcZUkABgB9S0Afzx/s4/tleJPg/fW
+l6/PdeIvCBwjWssm+ezX+9AzHoP+eZO04429a/S3wf4w0fx94bsde0C+j1HSrxN8NxHnB5wQQeQ
wIIIPIIINeY/8FHv+Cbmnaho2rfFb4T6T9k1a33XWt+G7JMRXMfJe4t0H3ZB95kHDDJADAh/h39j
n9o+5+DfjSHQ9UuN3g/WZ1juVkb5bOVsKtwvoOgf1UZ6qKloiUex+pNFFFQZBXyj+1V+2lafDB7z
wp4MeLUPFi5jub1gHg049xjo8o/u9FPXJBWun/bK/aKk+CPgmHT9FkUeK9bV47V85NpEOHnx68gL
njOTztIPxt+xz+yb4i/bC+K39lRTXFn4ds2F1r2vEbzBGxPyqTw00hBCg56MxyFNUkXGPVnI/Dv4
S/FX9rLx1ND4e0vVfGetyMpu9QncmK3U9DNO52Rr1wCR0woPSv0G+E3/AARItxDBdfEv4hTNIygy
ab4XtwoU9wLmYHP/AH6H1r9GPg/8G/CPwH8C2PhLwVpEOkaPajJVOZJ5CAGllc8u7YGWPoAMAADt
qs1PiOw/4I+/s+2dq0UsHia+cjAmuNWw49xsRV/SuK8df8EVPhbq1jJ/wifjHxN4c1A/da/MN/bj
6xhI2/8AH62v+ClX7bHxF/ZR8VeCNP8ABC6O1vrFlcz3P9p2bTtuSRFXaQ64GGNfeNpI01rDI33n
RWOPcUAfgP8AtLf8E3/i5+zjb3Grvp6eMfCcKl31vQkaQQKOpnhI3xgd2+ZB/e7Vn/s2/tqeIPhV
eW+jeK7i68ReEmIT945kubEdN0bE5ZQP4Ce3y46H+g1lDKVYAqRgg9DX5Tf8FJP+Cb+n6No+p/Fn
4T6V9lity1zr3huzT90kfVrq2QfdC9XjHAGWUAKQQW57j4Z8TaX4y0Gx1rRb2LUdLvYxLBcwnKup
/UEHIIPIIIPIrTr8zP2Jf2j7n4Y+MbbwhrFxv8Ka1cCNTI3Flctwsg9FY4Vh06N2Of0zrNqxi1YK
KK+Zf22v2jp/g/4Vg8OaBP5XinW4mIuFb5rK2+6ZR6Oxyqnthj1ApAtTmf2qv224fAst94Q8BTR3
XiKMtDeatgPFYt0KRg8PIO5+6p45OQPkj4UfAr4r/taeNLhPDOk6l4q1CSQG+1i8kP2eDPea4c7V
46LncQPlB6V3X7D/AOxrrX7X3xIe3mkuNM8E6Wyy63rMY+YZ5WCIkEGV8HrkKMsQeFb96Phh8LfC
3wa8F6f4T8HaPb6JoViu2K2gHLN/E7seXdupZiST1NaWsbJWPzm+Ff8AwRH0uGGK4+JHxDu7uUrl
9P8ADFusKo3oLiYMWH/bJa9ps/8Agj/+z5bWjQyW3iW6kIwLibV8OPcBUC/pX1r8QPib4S+FOhtr
PjHxHpnhnTAdoudTukhVm/uruOWb/ZGTXzxdf8FR/wBmi1vzat8RWk2kq00Wi6g8YP1EHI9xkUxn
ivj/AP4Io/DXVrFz4P8AGviPw7qHJU6msN/b+w2KsTD67z9K+Cf2lv8Agnr8W/2Zln1S/wBMXxN4
Ti+c+IdCDSwwr6zpjfDj+8w2c4DGv29+FH7T3wp+ODrF4H8eaNr14wLCwjn8q72jq32eQLJj324r
02aGO5hkhmjWWKRSjxuAVZSMEEHqKAPwE/Zp/be1r4c3cGheN7m61/wu5CJdyMZbqx7AgnmSMd1P
IH3em0/o3oeuWHiTR7PVdLu4r7TryJZoLmFtySIwyCDXzX/wUm/4Jx2Xw+02++K3wq01odBRmm13
w7bLlLFTybm3UdIs/fTomcjCZCeB/sK/tH3PgnxTafD/AFu48zw5q8+yxklb/jyum6KP9iRuMdmI
PGWzLRnKPVH6O1j+Mv8AkUNc/wCvGf8A9FtWxWP4y/5FDXP+vGf/ANFtUGZ+ItFFFanQfoX/AME0
P+Sd+L/+wrH/AOiRX2PXxx/wTQ/5J34v/wCwrH/6JFfY9ZvcxluFfm/+3L+0pP488TXPgLQbnb4a
0mfZeSxNxfXKnkE90jPAHQsCecLj7A/au+LTfB74L6xqlrL5Wr3uNO09gcFZpAfnHuiB3Huor8ld
PsLvWdRtrKzglvL66lWGGCJSzyyMQFVQOSSSBj3pxXUqK6nrv7KX7MPiT9qz4rWfhPQ1a10+PFxq
2rsm6KwtgcM59XP3UT+JvQBiP6Avgf8AAnwZ+zv4DtPCXgnSk03TofnmmbDXF3LjDTTSYy7nHXoB
gAAAAcN+xX+zLp/7LfwN0bw2LeH/AISa7jW9169jALT3bDJTd3SMHy17YXOMsc+9VZoFFFFABRRR
QAUUUUAfBX/BRL/gnjpfxv8AD+p/EH4faXHZfEq1Q3F1aWqhU1uNR8yso4+0Y+6/8WNrZypX8V7W
6vtA1WK4gkmsNRspg6SKSksMqNkEdwwI/Aiv6na/G/8A4K/fssxeAfHlh8W/DtgtvofiWT7NrEcC
YSHUQCwlIHA85ASf9uNyeXoA9V/ZX+PMfx4+G8V7dNHH4j04ra6pAmBl8fLKB2VwCfYhh2r2Wvya
/Y9+LD/Cn42aPJNKU0jWGGl3yk4ULIwCSH/cfac+m4d6/WWs2rGMlZhX5J/tafEy5+Knx016ZJTP
p+mztpWnxpyvlxMVJX13vub/AIEPQV+p/j7Wn8OeBfEerRv5clhptzdK3oUiZgf0r8u/2JfA9v8A
Ez9rX4YaJqCm4tZtaju542581YA1wyt6hhEQfYmnEqJ+2n7DP7NNv+y/8AdF8PTQRjxPfgalrtwo
BLXTqMx57rEu2MdvlLfxGvoOiirNDzb4zftHfDb9ny10+f4heLbPw2NQLC0jmSSWWbbjcVjjVmIG
5cnGBkc81+V37Qnw1/Y2+MnxO1HxjoH7QLeCTq1w13qOmp4bvLuF5mJMjw/JGY9xJYg7hknGBgC5
/wAFtmP/AAvHwAuTtHhxiB2/4+Zf8BX5y0Afuf8Asv8A7TH7JPwJ8D6J8NfA3xMtPKacs11qdrcw
veXMhG6WaV4UjBOFXkgAKo7V9s1/KvX9SPg9i/hLRGYlmNjASTyT+7WgDXr8FP8Agp1+zXB+z7+0
Rc3+jwLb+FfF6vq1hFGuFt5t2LmADsFdgwA4CyqO1fvXX59/8FovBFrrX7OfhrxKY86hoevpEkmO
kNxFIsi/i8cJ/wCA0AedfsX/ABMn+JnwH0ia+n+0anpLtpVzIx+ZvLAMZPqfLaPJ7kE17nXwh/wT
J1uQXfj3SGkJhZLS7jj7BgZVcj6gp+Qr69+M+uS+GfhD411WCQw3Nno15NDIvVZBC2w/99YrN7mL
3Pyt/aS+J1x8WvjJ4i1pp/PsY7hrPT1B+VbaNiseP97lz7ua6b9mv9tD4n/srzzReDNVt30S5n+0
Xeh6lbia0uHwF3Ho6NhQMoyngZzW9/wTn8CW/wAQv2zPhrYXah7WzvZNWcEZG61heeP/AMiRp+df
rf8AtA/8E2/gt8fPtN8+g/8ACHeJJct/bHhwLbl39ZYceXJk9SVDH+8K0Njy/wDZ9/4K+/C/4k/Z
tN8f2k/w41t8IbiZjc6bI3TiZRujz1+dQo/vmvPv+Cg3/BTjUPAetp4B+DGr6fLd/Zo59R8WWjRX
aIJE3JDbH5kJ2MrGTnG4AYIJHzF+0D/wSj+MXwd+06h4at4/iT4ejywn0WMreoo/v2hJYn2iMn4V
8ZXlncafdTWt3BJbXMLmOWGZCjowOCrKeQQexoA73XNY+Kv7Qd++p6pc+LPiJdWasDcTG51E2yHk
gH5vLXocDAr1b4L/ALZ37SngnxrpWh+HPGPiPxHqctwlpB4d1ovqQnckAQ+XLl1zwPkKkdiK+l/2
Ff8AgqF4L+Cvw38P/DTxx4Um0bTNNDpH4h0UecsheRnL3EHDZyxyyFyePlFfpN8O9Y+EHxw1iy+J
fg5/DPirWrWBraPX7KOKS9to3HMbtjzIyQMbXwQCRjBOQDsvAF54j1DwTolz4v06y0nxPNaRvqNj
p05nggnI+ZEcgZAP19AWHJ32UOpVgGUjBB6GlooA/n3/AOCin7N0X7Nv7R2qWWlQiHwtr6f2zpCI
MLBHI7CSAenlyKwA/uFPWvtT9lD4lz/FT4G+HtWvZ/tGq26tYXshOWaWI7Qze7JsY+7Vof8ABbfw
Ra3vwh+H3i/y/wDTtN1yTSxIB/yzuIHkIP0a1XHpk+tfOn/BMnW5JvD/AI80hpCYba6tLtI+waRJ
FYj8IU/IVMtiJbH2vJIsMbSOwRFBZmY4AA6k1+PXxM8U6z+0R8dLu5ske+vtc1NNP0m1HHyNIIre
IZ6ZBXPuSe9fp/8AtIa5L4b+A/ju/gkMMy6TPEki9VaRfLBHvlq+JP8Agl34FtfHX7Z3gz7bH5tv
o6XOr7MceZFE3lH/AIDI0bf8BFKIon7TfsyfAfSv2bfgr4c8CaWI5JLGHzL+8RcG7vH5mmPfluFz
yFVV7Uv7TPx80f8AZp+DOv8AjzV0+0/YoxFZWIba13dP8sUQPYFuSeyqxwcV6lX5A/8ABZL456t4
i8QeF/hnP4a1jw9aaRcz6lJdX2w2uq7lWOCa3ZGO5VBnB3AMpfBAOas0PhP42fHLxn+0L46u/FXj
XV5tU1GdiIYckQWkZORDBHnCIPQcnqSSST6X4R/4J5/tEeN9BTWdM+F+qJYyJ5if2hPb2Mrr6iKe
RHOe3y89qn/4J46Paat+1n4Ka78Jah41W0kkuYtMsYo3VZQpEc8xkZVSKJmEhYnqigAkgV/QxQB/
MN408A+Nvgb40TTPEmk6r4P8S2ey5iSdWgmTnKSxuOoyDhlOMg88V+r/APwTI/4KBal8YrmP4VfE
i/F34thgL6NrUx/eanGikvDMf4plUFg/8aq2fmXL+p/8FU/gppnxP/ZX1zxA9vEuv+ECmq2V35Y8
zytwSeLd1CMjFsdN0aHtX4gfDnx1qfwx8feHvFujytDqei30N/AynGWjcNtPscYI7gkUAf1BXFvF
eW8sE8STwSqUkikUMrqRggg8EEdq/ng/bo/Z5b9l/wDaQ1vw7p+6LQbvbrGhupIZLWVm2pn1jdJI
89T5YPev6FNB1m28R6Hp2rWbF7O/to7qFmGCUdQyn8iK/Mr/AILfeCLWTw/8MfGCR7b2G6utJlkA
+/G6LLGD/ulJMf75oA6T9nH4jyfFb4L+GPEVzIJdQmt/IvGHBM8bGN2I7biu7/gQrsvGX/Ioa5/1
4z/+i2r5U/4Jp63JdfDfxXpTyFks9USdFP8AD5sQBx7Zi/nX1X4y/wCRQ1z/AK8Z/wD0W1Z9TB6M
/EWiiitDc/Qv/gmh/wAk78X/APYVj/8ARIr7Hr44/wCCaH/JO/F//YVj/wDRIr7HrN7mMtz8+f8A
gpV41e98a+FvCsch8iwsnv5kU8GSVyq59wsX/j/vTv8Agk38IU+Jn7WGnazeWyz6Z4Qs5dZfzFyh
uOIrcf7weTzB7w15l+3dqX9oftLeIos5FnBaQD/wHRz+rmvuz/gh7oKw+DfirrRjG+5v7GzEmOcR
RyuRn/tsKtbGsdj9O6+bP20v23PC/wCyD4Vt2ubf+3vGWqIx0vQo5Nm5QcGaZuSkQPHTLEEDoxX6
Tr+cX9tT4sXvxm/ag+IPiC6naa2j1SbTrBW6R2lu5ihAHbKpuP8AtMx70xncfEP/AIKa/tDfEDVJ
rlfHMnhm0ZiY9P8AD9tHbRRA9g+DI3/AnJqx8O/+CoH7Q3gHVIribxmviqzX7+n+ILSOeOQe7qFl
H4OK+1P+CTP7JPgub4KxfFbxPoGn+Idf1y7uI9OfUYBOlnawyGI7EcFRI0schL4ztCgEfNn6I/a6
/YK8C/tQeEFt7ay0/wAI+L7eWNrTxHZ2C71TcPMjlRSvmoV3YBPytggjkEA0v2Mv21PC/wC2B4Pu
rmxtm0PxXpaoNV0OaQOY93SWJv44iQRnAIIwR0LeN/t3f8FMrH9nHV5/AvgOztPEXj2NAb24uyWs
9L3DKqwUgyS4IOzICgjJP3a7r4Z/smfDL9gP4U+M/H2gWlzrXinSPD95d3Wu6pJummWKIymJEXCR
ozRjgDJ4yxxX4OeINe1DxVr2pa1qt1Je6pqNzJd3VzKctLLIxd3PuWJP40Ae/eIf+CiX7RXiTUmv
J/ijq1oxbcIdPjhtYl9AEjQAj659816Z8F/+CtXxt+HesW48V39r8QtCMi+fa6lbpDchP4vKniVS
G93Dj2r9PP2Qf2OPAfwE+EPh22fwzpeoeLbqziudX1i7tVmnluXQF1V3BKxqSVVVwMDJGSSfOv2m
v+CWvw9/aA+ImieJtKuk+H6guuuQaLZIP7RXgoyLkJFLncC+1twIyCRyAfSvwF+OvhX9oz4aab43
8IXTzaZebo5IJwFntJl+/DKoJ2uuR3IIIIJBBON+1r8J1+N37OHj/wAHrALi9vdLlksUK5P2uIeb
Bj0/eIg47E1f+Af7OPgP9mnwi/h7wHpB021ndZbu4mmaae7lAx5kjseTjsAFHYCvTaAP5WASrAgk
MD+Ir9nfgr4xb4gfCXwl4gkfzLi+02F529ZgoWX/AMfDV+TPx20MeF/jd8QtGVBGuneItRtAgGAo
juZEx+lfpB+wzqX9ofsz+FUJy9s93A34XMjD9GFTIiWx6J8cbOTUPgt49toiRLLoN8i49TbvxXwJ
/wAEyNRh0z9uL4ZSzKpWSW+gBPZnsLhFI/Fh+dfpPqumw6xpd5YXAJt7qF4JAOu1lKn9DX4/+CfE
Op/s4/tB6TqxDHUPB/iBHmRePNEE2JE+jqrD6NSiKJ/TBRVLRNasfEmi2GraZcx3um39vHdWtzCc
pLE6hkdT3BUg/jV2rND8cP8Agtt/yXPwD/2Lh/8ASqWvzmr+nb4leBfDXijQdTu9a8PaVq91BYzL
FPf2UU7xjYxwrMpIGeeK/mJoAK/qQ8G/8ihof/XjB/6LWvy1/wCCLPgnw74v0f4ttr2gaXrbW8+l
iE6jZx3Bj3Ldbtu9TjOBnHoK/WCONYo1RFCIowqqMAAdhQA6viv/AIK8ahFZ/sa6nDIoL3es2EMR
PZg5fI/4CjfnX2pX5cf8Ftvi1HFovw++GlrcK0088uv38Kt8yKimG3yPRi9x/wB8CgD5o/4Jn2kj
+PfGV0CfKj0yKNh2y0uR/wCgGvrz9pqzkvv2fviBHGSGXR7iU49EUuf0U14F/wAE1fBsmneBfFXi
eVSv9qXsdnCD3SBSSw9i0xH/AACvrTxZ4fh8WeFdZ0O4YpBqdlNZSMOoWRGQn8mrN7mMtz4D/wCC
TupRWP7bHhOGRQXvLHUYIyezC1kkyPwjb86/eev5rvgF48u/2df2lPCXiO93W0nhvXVj1FRnIhDm
K6T6mNpF/Gv6S7S7gv7WG5tpo7i2mRZIpomDI6kZDAjgggg5rQ2Jq8d+O37I3wp/aOtHXxt4StLz
Utm2PWbUfZ7+LjjEyYZgOyvuX2r2Hpya/KP9qT/grxrnh74yWulfCSCxu/Cmg3LR6jcalblhrLjK
sidGjiXnay4ZmGfu8EA5H9oL/gjT4z8J/adT+FOuReM9NXLLo+pslrqCD+6snEUp9z5Z9FNfC8N5
8QP2efiFPHDNrngHxjpb+XKqPJZ3UOQG2sBglWBBweGBHUGv1q8Jf8FqPhHqWmq/iHwp4s0TURGG
eG1ht7uEtjlUk81GPPQlF/CvzQ/bM/aMg/ak+POr+ObLSZNF02SCGzs7Wcq03kxLgNIV43sSTgE4
BAycZIB9Wfs/f8FlvGfhP7NpnxW0OLxnpq4VtY0xUtdQQerJxFKfYeX7sa/Sn4E/tdfCj9o61Q+C
fFtpd6kU3SaNdn7Pfxcc5hfDMB3ZNy+9flt8Nf8Agkf4w+Kn7Ovh3x1p/iKHRPF+qxSXY8O61btH
E1uWPknzVyyMyAPgoQQ68rg18ofFr9n/AOJ/7N/iCGLxl4Z1TwxdRy5tdRUE28jg5BhuIyUYjGfl
bI74oA/Wv/gsxeQ2/wCybpcUm0yT+KbNIs9dwguWJH4Kfzr4n/4Jj2cjal8QrrJESQ2MRHYlmnP6
bT+dfOXxI/ag+Jvxf8AaN4O8aeK7zxLo2j3Ru7M6hiS4RyhT5piN8gwTjeWIyea+zf8AgnH4Nk0X
4R6v4gmUq2t6iRF6GGEbAf8AvtpR+FJ7Ey2PUP2wLOS+/Zs8dRxkhltI5Tj0SaNz+imvnD/gjvqU
Vj+195MiqXvPD19BET2YNFJkf8Bjb86+zviT4TXx58PvEnhxm2HVNPntFc/ws6EK34Eg/hX5efsf
/FJvgH+1J4E8TX8n2G0sdVFlqZlOBFbzZgnLf7qSM31UUoiif0eV5J+0x+zP4Q/am+HFx4V8VW+y
Vd0um6tCoNxp8+MCSMnqDwGQ8MODzgj1lXWRVZSGVhkMDkEetfnP/wAFlfBfieH4feC/iF4b1HUb
G10W6l07VRYXEkf7ufYYZH2kDarxsmT3mUVRZ9O/sgfseeE/2RvAf9l6Tt1XxLfKrav4gliCy3bj
oijJ2RLztTPuSSSa99r+ej9jf9rbVfgL+0F4c8U+KNY1jV/DH7yz1S3e7kmIglUr5gRiclG2vjqd
hA61+5Hhz9qD4Q+LPD6a1pnxM8Kzaa0fmtLJq8EJjX/pojsGjPqHAIoA5z9uPVLfR/2Qfi5Pcqrx
v4durcBv78qeWh/BnU1/OTX6b/8ABUr9vPwv8TvCsfwl+HGrLrmnSXMV1ret2Uga1mVPmjtomH+s
G/a7MOAUQAn5sfGf7HPwAvv2kv2gPC/hKG3eTSRcLe6xOqkrBYxENKWPbdxGuf4pFoA/oG+BtjPp
fwT+H1ndFjdW/h7T4Zdwwd620YbP4g18Rf8ABbTUIo/gD4GsSo8+bxOJlbuFS0nDD85F/IV+iaqF
UKowBwAK/Hn/AILVfFqPXvir4M+HtpcLJF4e099QvUjbO24uSAqMOzLFErD2m96AOU/4Jj2kiaP8
QLok+VJcWUSjtlVmJ/8AQxX2J4y/5FDXP+vGf/0W1fPf/BPbwa/hz4EnVplIl13UJbpM8fukxEv6
xufoRX0J4y/5FDXP+vGf/wBFtWb3MXufiLRRRWhsfoX/AME0P+Sd+L/+wrH/AOiRX2PXxx/wTQ/5
J34v/wCwrH/6JFfY9Zvcxlufk9+2xYNYftNeMg2SsrW0yk9w1rEf55H4V+iv/BEbVkm+DnxE0wBf
Mt9eiuWPfEluqj/0Uf1r4c/4KJ+HZdL+OttqRX9xqmlQyK/bcjPGw+oCqf8AgQr3/wD4In/E+HQ/
it468CXDKn9v6bDqFsW7y2rsGQe5S4ZvpFVrY1Wx+w1fzFfGrQLnwr8YvHWjXiNHdafrt9ayK/Xc
lw6n69K/p1r8kf8Agqz+w/rkXjC/+NPgfS5dT0nUEV/EVjZx7pLSZVC/ago5MbqBvIHysCx4YkMZ
9af8EqfFll4k/Yp8G2ltNHJdaLc32n3kcfWOT7VJMoI9THNE3/Aq+p/E3ibSvBnh7Udd13ULfStH
0+Brm7vbpwkcMajLMxPav5zP2df2tPiV+y5ql7deBdaW3tb4D7Zpd7EJ7S4I6M0ZPDDpuUhscZxx
XX/tFf8ABQL4v/tNeHl8PeJtTsdM8OF1km0nQrY28NwynKmUszu4BwQpbbkA4yAQAfth+0mbT4pf
sk/ExvDN9b63ban4V1B7G506dZork/Z3KhHUkMCRjg96/m+6V+xX/BJj9lz4hfDXQdW8a+NLzVtD
0LWrcR6b4QuJmWKdWwWvJ4DwrYAVAQGIZieCufib9vj9iTX/ANmH4jalq+labNd/DPVblptM1KFC
0dnvJP2SYj7jJnCk8OoBByGCgH7s+AfFlj488D+H/EmmTR3Gn6vYQX0EsR+VkkjVxj8DUfjL4ieF
/h1Dp03inxBpvh6DUbtbG0l1K5SBJp2VmWNWYgbiFbA9q/BH9nv/AIKH/GT9m/wxH4a8PapY6v4d
hYtb6Zr1s1zHbZ5IiZXV1Uk52htuSSByc8l8a/2jPiv+2V440iPxHcza9f7/ALNpOgaRalYY3cgF
YYVyWdiBliWY4AzgAAA/o8Vg6hlIZSMgjoaWvmL/AIJ7/s/+NP2ffgLaaV4816/1HXb6QXP9kXF4
bi30aLGEtoeSAerPtO3ccD7u5voHx14usfh/4J1/xPqbbNO0Wwn1G5bOP3cUbSN+imgD+cT9qjVE
1r9pr4s30YAin8Waq6bf7v2uXB/LFffH7A9i1p+zdo8rZxdXl3MufQSlP5oa/MbxFrlx4m8QaprF
3t+1ahdS3c23pvkcu2PxJr9aP2TdAl8N/s6eBLOZNjvYfa9vtPI0w/SQVMiJbHrVfnb/AMFC/gq3
hnxjbfEDTYT/AGbrZEF/tHEV2q8N7B0X80Y96/RKsXxp4N0j4g+F9R8P67aLe6XfRGKaJuvqGU9m
BwQRyCAalaGadmecf8Ek/wBs2x1fw3a/A/xbe+TrNj5jeG7qd/lurfl2tMn+NDuZfVDtGNgz+m9f
zafHD4IeKv2avH8TLLdx2SXAuNG8QWpMZYqQyEOv3JUIGRkEEZHGDX6J/sZf8FbNI1bS7Lwl8cLo
6ZrEW2G38WpDm3uh0H2pVGY36fvFGw5y2zGTobn6ReLP+RV1n/rym/8ARbV/LbX9SMN7pnjfwwZ9
L1G31HS9StmEN9YzLNFIjqRvR1JVhz1Br87/APhyH4E/6KT4i/8AAOCgDn/+CG//ACBfjF/18aV/
6Dd1+o9fOP7HP7FWh/sc2niqDRfEeoeIR4ge2eVr+GOPyvJEoG3Z1z5p6+grX/aO/bW+Ff7MNjIv
irXlutf2boPDul4nv5eOMpnESn+9IVBwcZPFAHoPxm+MXhn4D/DnV/Gvi2+Flo+nR7iFwZZ5DwkM
S5+Z3PAH4nABI/nj+MHxK8T/ALWX7QGp+I54Gl1nxJqCwWOnq+5beIkJBAp9EQKC2BnDMeprqf2q
v2vvHv7YfjeGbVvMs9Dhm26P4XsWZ4bct8oJAGZZiDguRnkhQo4r6n/Yw/ZTb4WWC+MPFlmq+Lrt
CttaSYJ06EjnPpKw6/3R8vdqTdhN2PffhH8ObL4S/DnQ/ClifMj0+ALJNjHmysS0kn/AnZjjsCB2
rr6KKzMD82P2/vgqfA/xETxnp0JGjeI2LT7R8sV6Blwf98fOPU7/AEr7n/4JQftnWXj3wRY/BrxT
e+V4s0KBl0Wa4f8A5CFivIiUn/lpCvG3vGoI+41bvxC+H+i/FDwhqPhvX7UXWnXqbWxw8bdVkQ9m
U4IPt6cV+U3xV+FPjP8AZh+JFuwuLuxltbj7To3iCyZovN2MCsiOD8ki8ZXOQfUEE2maxfQ/pSr5
l/aK/wCCd/wd/aS1C41nV9IuPD3iec7pdc8PyLbzTtjrMhVo5D0yxXdxjdXzv+xz/wAFavDvi7S7
Hwv8arqPw94lj2wx+Jli22F72DThf9RIe5x5Z5OU6V+jGmapZ61p9vf6ddwX9jcIJIbq1kWSKVT0
ZWUkEH1FUWfgP+3p+xnYfsc+KPC2nad4oufEtvrlrPcg3VosDweW6rtyrENnd1wOlfo5+z//AMEl
vhJ8K9UsPEPiK5v/AIharCEmhh1RUisY5Bgh/IXO8+zuy/7NfRvxr/ZT+Ff7RV/pd78Q/CieI7nT
InhtJGvbm38pHILDEMiA5IHXPSvV441ijVFGFUYA9hQAvTgcCvL/ANpX4qeBPg78Hde8Q/EWKzvv
DqRGI6XeRJMNRlIOy2SNwQ7MR0IwACxwFJHD/tLft3fCn9mG1uLbXNZXWfFKoTF4b0hlmuy2OPNO
dsK9OXIOOVDdK/FD9pH9qD4hftifESC+1xpZIBKYdG8N6cGeC0DEAJGg5eRuNzkbmOOgAUAHAw6b
d/Gb4rtaaBo1npNz4g1Nvsul6ehS2s1kckIg7RxqevZVzX6/fDvwPYfDXwPovhjTAfsemWywKzDB
kbqzn3ZizH3Jrwn9jn9llfg1ov8AwkniS3R/Gl/Ht8s4YafCf+Wakcbz/Ew/3Rxkt9MVDZlJ3Cvz
C/bq+CrfDX4qSeIbCEroXiVnu1Kj5YrrOZk9skhx/vED7tfp7XJ/FL4Y6J8XvBV/4Z16DzLS5XMc
qgeZbyj7kqHsyn8wSDkEiknYlOzLn/BLP9s6y+MHw5sfhf4lvfL8deGrURWj3D86nYpwjKT1kiXC
sOpUK3Pzbftzxp4N0b4h+E9W8M+IbCLVNE1W2e0vLSbO2SNhgjI5B7gjBBAIIIr+cLxx4F8d/sr/
ABStZFubvRtX0+f7TpOuWLGNZgp4kiYexwynpkgjnn9Sv2P/APgrJ4R+Iml6f4b+L11B4R8XriEa
2ybNNvz0Duw4t3PfdiPuGXIUaG58nftRf8EofiX8KtdvNR+HNjcfEHwdI5eBLTB1K1UniOSHgy44
G+MHOMlV6V8lan8EfiLouojT9Q8A+KLG/PS1udGuY5T/AMBKZr+m2zvLfUbSG6tJ47q2mQSRTQuH
R1IyGVhwQfUVNQB/Pl8Ev+Cc/wAc/jXqVssfg+78JaNIcyax4mjayiRfVY2Hmye21CD3IHNfsx+y
T+yH4Q/ZH8Bvo2g7tS1y+2SavrtwgWa9kUHAAydka5bagJxkkkkkn3WvmX9p7/goJ8Kv2Zba7sb3
VF8T+MY0Pl+G9HkWSVXxwJ5OVgGcZ3fNg5CNQB6L+0t+0Z4Y/Zg+Fmo+MvEsvmGP9zp+mxuBNf3R
BKQp+WWb+FQT2wf59VbxV+1L8d5Z7yY3fiXxZqbT3M+CUiDEs7Y7RxoDgdlQAVufHj9oT4jftifE
6DUdfkm1K8lkNvpOg6cjGCzViP3cMfJJOBuY5ZsDJwAB9zfsi/sww/A3w2dW1qKObxpqUYFy4IYW
cRwRAhHfoWYdSABkKCU3Ylux7h4P8K2HgfwrpPh/S4zHp+m20drCrHJ2qoGSe5PUnuSaTxl/yKGu
f9eM/wD6Latisfxl/wAihrn/AF4z/wDotqzMT8RaKKK1Og/Qv/gmh/yTvxf/ANhWP/0SK+x6+OP+
CaH/ACTvxf8A9hWP/wBEivses3uYy3PlL/goh8NH8VfCqw8UWkJkvPDtyTNtHP2WXCuffDiI+w3G
vh39nz4yaj+z/wDGbwp4/wBMj8+fRbwSyW+cefAymOaLPbdG7rnsSD2r9g9a0ez8RaPfaVqEC3Nh
fQPbXEL9HjdSrKfqCa/Hz48fB/Ufgj8R9S8OXiySWit51heOuBc27H5H9Mj7rY6MpqolxfQ/pK8E
+MtJ+Ing/RvE+g3a32javaR3tpcL/HG6hlyOx5wR1BBB6Vt1+OH/AAS3/buT4X6pafCDx5fLF4R1
CcjRNTnbC6bcyNkwuT0hkYkg/wADsSeGJX9j6os8N8f/ALD/AMCPidqUuoeIPhhoc1/MxaW5so3s
pJWPJZ2gZCzH1OTVz4b/ALGvwT+EeqQ6n4V+G+iafqcP+pvZomup4j6pJMzsp9wQa9mooAKrajpt
prFjcWV/aw3tlcIY5re4jEkciEYKspGCCOxqzRQB87eIv+Cef7OnijUGvb34VaPDMzbiunyT2Uef
+ucEiIB7YxXofws/Zz+GXwTMr+BvBGjeHLiUbZLq1tgbh1/umZsuR7bsV6NRQAV8C/8ABXj9pCD4
a/BOL4a6bMp8ReNOLhVPzW+nxuDIx9DI4EYz1Hm+lfWX7QXx88Lfs2/DHVPGviu58u0tRstrONh5
17cEHZBED1ZiPoACx4BNfzy/tBfHbxL+0f8AFTV/HPiiVTfXrBILWLPlWduufLgjH91QevUkljyT
QBz/AMMvA938SviBoHhizVjNqd2kBZRkxxk5kf6KgZj7LX7Safp8Gk6fbWVrGIbW2iWGKNeiooAU
fgAK+L/+CePwLk0uxuviVq9uUnvEa00iORcEQ5/eTf8AAiNqn0DdmFfbFZyMpPUKKKKRBi+MvBei
/EDw7d6F4g06HU9Lul2yQTD8mU9VYdQwwQelfAvxr/4J6+IvC7T6l4AuW8S6Zkt/ZtwVS9iHop4W
UD22t6Ka/RSincabR+Ofh3x18VP2ddcZdI1jxP4A1Hdue3jlms/Mx/fjOA4+oIr1vTf+Cm37S2l2
7QxfE2aVSMA3Ok2EzD33PAT+tfpLqui6frtqbbUrG21C3znybqFZUz64YEVx958BPhpfzCWfwB4Z
kkBzu/smAE/XC8/jVcxfMfm542/bi+PfxGsZLHWvijr8lrNw8FjMtksgP8LCBUyPY8Vl/Df9ln4m
/FrUI3tNAurCynbe+rawrW8GD1fLDdJ/wANX6oaL8NvCPhuaObSPC2i6VLHykllp0MLL9CqjFdHS
5g5jwL9nv9j3wt8DZE1aeQ+IvFO3H9o3EYVLfI5EEfO3PTcSW9MAkV77RRUkBRRRQIK57x78P9B+
Jnhm60DxJp0WpabcDmOQYZG7OjDlWGeGHNdDRQB+cPxq/wCCffinwhJNqHgaZvFek5z9ifal9CPp
wso91wf9nvXinhX4lfFf9nXWmh0TXvE/gK+B3SWaSzWof/fhbCuP95TX7E1S1bQ9O163Fvqen2uo
wA5EV3Csq59cMCKrmLUj83LD/gpx+0vp9q0EfxNmkUjAa40iwlce+5oCf1ri/HX7anx2+KFm2na7
8TfEF1azHa9rZzi0SXP8LJAEDD2IIr9Kbr4C/DW8mE03w/8ADMkgOdx0i35+vyc/jW7onw/8L+GZ
ll0fw3pGlSr917GwihYfQqop8w+Y/LP4Y/sj/Ez4p3sTRaDcaLp0h3PqmtI1vHt/vKGG98/7II9x
1r76/Z9/ZL8KfAZf7QjZtd8TOm19WuowvlAjBWFOfLB7nJY+uOK9woqbkuTYUUUUiQooooA5b4kf
DPw78WfC9xoPiXT0vrGX5kbpJC+OJI26qw9fwOQSK/P/AONH7APjDwRLLfeDWbxho2ciBAEvoR6F
Okn1Tk/3RX6U0U07DTaPx58HfF34tfs76o9roHiXxN4GulOZNPWaW3Qn1eBvlb/gSmvV7P8A4Kdf
tMWVo1unxMldSMB5tH0+Rx/wJrcmv0g1jw/pfiGBYdV02z1OFTkR3kCSqPwYGuTn+Anw0urgTy/D
7ww8o53HSLfn6jZz+NVzF8x+aHjz9sT44/Fq1/s3xB8SfEOo2sx2tY2tx9mimz/C0cIQP9CDVj4W
fsc/Ev4oXkLHRZvDmlN8z6jrUbQLt9UjI3uT2wMepFfqNofgXw14ZkEmj+HtK0mQDAaxsooSB6ZV
RW5S5g5jxv4A/steE/gHbNcWIbV/EMybJ9Yu0AfHdIlH+rU+gJJ7k4GPZKKKkzCsfxl/yKGuf9eM
/wD6Latisfxl/wAihrn/AF4z/wDotqAPxFooorU6D2L4IftTeLfgFo+o6Z4dstHuoL64FxK2pQSy
MGChcKUkXjA9K9J/4eQfE7/oEeFv/AO4/wDj9fKlFKwrI/VD9kn9p8/tAaLqNprUVnYeK9ObzJbe
zDLFNbscLIiszHg/KwycHaf4sDr/ANoj4C6V8fPAsulXWy11i13S6ZqJXJglx0Pco2AGH0PUCvyo
+GXxI1n4T+NdN8T6FMIr6zfJR+Y5ozw8bjurDj9RggGv1y+Dfxe0T42eB7PxHokm0SDy7qzZgZLW
YD5o3+nUHuCD3qWrGbVndH4/eMfBuseAfEl9oOvWMunapZyGOWGUY+jKf4lI5DDgg5Fffn7Cf/BU
i++FMNj4E+Lt1dax4PjUQ2HiDa013pijgRyAZaaEdsZdBwNwwF9r+PP7O/hn4+eH/surRfY9Xt1I
sdYgQedbnrg/30J6ofwwea/MP4xfATxh8ENYNp4i01hZO5W21S3Be1uB22v2OP4Www9KpO5alc/p
F8D+PvDfxM8N2uv+FNcsfEOi3IzFe6fOssZPdSQeGHdTgg8ECt+v5kvhL8dfH/wK1p9V8BeK9R8N
XcgAlFpIDFMB0EkTApIB23KcV9qfDP8A4LTfE7w3brb+NPCWh+NFQYFzbO2m3DH1YqHjP/AY1plH
7M0V+ZGk/wDBcLwzNCTqfwq1a0lxwtpq8U659MtEn8qxNf8A+C4yeXImifCFi5B2Tahr/APbMaW/
P/fQoA/VKvnP9qL9u74Yfsu6bd2+rarHrnjBYybfwxpsge5ZiPl85hkQL05fnHKq3Svyb+Ln/BUj
4+fFWO5tLfxFb+CtLmBU2nhm3+zvtPH+vYtMDjurr9K+TZJLnU71ndpbu7uJMszEvJI7Hqe5JJ/H
NAHqf7SH7Tvjn9qLxzJ4i8Y6huijLLYaTbkraafET9yJM9TgZc5ZsDJ4AHV/so/ss6h8cNfj1bV4
ZrPwTZSZuLjBU3rA/wCpiP8A6Ew+6OOpFegfs1/sI6n4ourbxB8R7WbSdEXEkOisSlzdd/3uOYk9
uHP+z1P6CaXpdnoem22n6faw2NjbRiKG3t0CRxoBgKqjgCpbIlLsJHHY+HtJWNFh0/TbGDAUYjig
iRfyVVUfQAV8BePf+CjniyHxhqsXhLStDk8OxTGOyl1C2meeVBxvYrKoG4gkDHAIB5Ga3v26P2pV
kS9+GnhS6Dqf3et30LZHvaof/QyP93+8K+F6SQox7n1X/wAPIPid/wBAjwt/4B3H/wAfo/4eQfE7
/oEeFv8AwDuP/j9fKlFVZF8qPqv/AIeQfE7/AKBHhb/wDuP/AI/R/wAPIPid/wBAjwt/4B3H/wAf
r5Ur6uX/AIJa/tMyKrL8OoyGGR/xPtO/+SKLIOVDP+HkHxO/6BHhb/wDuP8A4/R/w8g+J3/QI8Lf
+Adx/wDH6yfFf/BN/wDaP8G6TPqN/wDDG+uLWFd7/wBmXtpfS4HpFBK7n8FNeffA39mH4j/tIXmr
2nw+0KHXLvSVR7y3k1K1tZI1ckKwWaRCwypBK5wcZxkZLIOVHq//AA8g+J3/AECPC3/gHcf/AB+j
/h5B8Tv+gR4W/wDAO4/+P188fEf4ceI/hH421Xwj4t0uTRvEOlyCK6s5GVyhKhgQykqylWBDKSCC
CDXpfwY/Yq+Mv7QPhKbxP4F8HNq+hQ3D2rXs2oWtopkUAsFE0qFgAwywBGcjOQaLIOVHef8ADyD4
nf8AQI8Lf+Adx/8AH6P+HkHxO/6BHhb/AMA7j/4/Xy3f2cmm31zaStG0tvI0TtDKsqEqSCVdSVYc
cEEg9Qagosg5UfVf/DyD4nf9Ajwt/wCAdx/8fo/4eQfE7/oEeFv/AADuP/j9fKlFFkHKj6r/AOHk
HxO/6BHhb/wDuP8A4/R/w8g+J3/QI8Lf+Adx/wDH6+VK3PAvgnWfiT4w0fwt4dtBf65q9ylpZWpl
SLzZWOFXe5Crk9yQKLIOVH0f/wAPIPid/wBAjwt/4B3H/wAfo/4eQfE7/oEeFv8AwDuP/j9eX/HT
9lD4qfs2W+kz/ETwq+g22qtIlpOt3b3UbsgBZS0MjhWwwIDYJGcZwcZHwQ/Z98eftG+Jr3w/8PtE
XXdWs7Rr+e3a8gttsIdELbpnRT80iDAOeenWiyDlR7P/AMPIPid/0CPC3/gHcf8Ax+j/AIeQfE7/
AKBHhb/wDuP/AI/Xzp8QPAWufC7xpq/hTxLZDTte0mc215aiVJfLkABI3oxU9eoJFezfBf8AYD+O
Px40K017w14NeHw9dcw6rqt1FZwyL/eRXYO6/wC0qkHB5osg5UdL/wAPIPid/wBAjwt/4B3H/wAf
o/4eQfE7/oEeFv8AwDuP/j9cd8cv2GvjP+zxpJ1jxd4QlGgqcPq2mTJeW0XOB5jRkmMEkAFwoJOB
zXgtFkHKj6r/AOHkHxO/6BHhb/wDuP8A4/R/w8g+J3/QI8Lf+Adx/wDH6+VKKLIOVH1X/wAPIPid
/wBAjwt/4B3H/wAfo/4eQfE7/oEeFv8AwDuP/j9fKlFFkHKj6r/4eQfE7/oEeFv/AADuP/j9H/Dy
D4nf9Ajwt/4B3H/x+vlSvqb4Y/8ABM39oD4peHrfW7PwjHomnXKeZbtrt4lpJKpGQREcyAHsWUZ+
lFkHKiX/AIeQfE7/AKBHhb/wDuP/AI/R/wAPIPid/wBAjwt/4B3H/wAfrzb47/sifFj9m1YJ/Hfh
O403TJ3EUOq28iXNm7kEhPNjJCsQGwrYJwSBivHaLIOVH1X/AMPIPid/0CPC3/gHcf8Ax+j/AIeQ
fE7/AKBHhb/wDuP/AI/XJ69+wZ8dPDPwtk+IupeBpLbwlFpyarJef2jaNIls6qwdoRKZRhWBIK5X
nIGDXgFFkHKj6r/4eQfE7/oEeFv/AADuP/j9H/DyD4nf9Ajwt/4B3H/x+vlSiiyDlR9V/wDDyD4n
f9Ajwt/4B3H/AMfqtqX/AAUS+JWqaddWU2k+GFiuYnhcpaXAYKwIOP3/AFwa+XaKLIOVBRRRTGFF
FFABXefBv40eJPgf4sj1vw/c4VsJd2MpJgu4wfuOPzww5B6d88HRQB+wPwP/AGi/CPx40cTaLdfZ
dXiQNd6PdMBcQHuQP40z/GvHIzg8V6Nq2j2Gv6dPp+p2VvqNjOu2W2uolljkHoysCDX4jaHruo+G
dWttT0m+uNN1G2ffDdWshjkjb1DDmvsP4N/8FFtU0hYdO+ImmtrNuo2jVtNRUuR7vFkI/wBVK/Q1
HL2MnHsesfEr/gnn4D8WSTXfhq8u/CF453eVEPtNpn/rmxDD8HAHpXgHiD/gnL8SNNuH/szUtD1i
3/hYXDwyH6qyYH/fRr7j+Hv7Q/w7+KMaf8I/4psZ7ph/x43D/Z7ke3lvhj9Rke9ei0rsXM0flNf/
ALDfxnsXwnhNLtc432+pWpH5GQH9KtaT+wd8Y9RkCz+H7TTFP/LS71KAj/yG7n9K/U+inzMfMz4G
8E/8E0dUmkil8W+L7W0jzl7bR4GmZh6CSTaFPvsavqb4T/sy/D34N7J9B0RJtUUf8hXUCJ7r/gLE
YT/gAXNejavrmneH7J7zVL+1020QZa4vJlijX6sxAFfPHxN/b3+G/giOeDRJpvGGqICFj08bLbd/
tTMMY90D0tWK7kfR91dQ2NrLc3M0dvbwqXkmlYKiKBksSeAAO5r4Y/am/boiurW68KfDS9Yh8xXn
iGPK8dClsevP/PT/AL57NXzx8aP2pvHfxuaS11W/XTtCLbl0fT8xwcHjec7pD0+8cZGQBXkFUolq
PcVmLMWYkknJJ70lFFUWFFFFABX7+f8ABQvxP8YvCfwM8O3fwSh1yfxS+u28V0vh/TPt8/2M2twX
LR+W+E8wQ/NjrtGeefwDr96v+ClP7Qvjf9mv4A+GvEvgLUodL1e78Q2+nTTT2sdwDA1pcyFdsikA
7okOevHvQBxf/BPP4i/tMaxqni+5+PttqWn+DLTT/tFtqHifTotNmhuFcbgPkjYx+XvZmYEDauCM
nP583n7U9n8F/wDgoB4r+KngAi58LyeILoT29qwEWpWMkmJ9vQYkIMiE9G2HtX1p/wAE9f28vi5+
0h8an+H3j2003xV4cvNOuZ7u7TTEie0Cp8u/ZiMxsfkIZckuvPY/H/8AwUq+E/hf4O/tYeItH8I2
sGnaTd21tqR022G2KzllTLxov8KkjeFHAEgAwAAAD79/bw/Y5g/bW0j4c/FD4WT2tzqWofZbW6vQ
Qsdxpc7Apct3LQFySv3trMOqAVn/ALf/AMYND/Yt/ZZ8PfAr4eS/YtZ1fTjYK0bATW+n8i4uXI6S
TuXXPctKwwVFJ/wRX+I2t+JPg7408KajdG50rw3qMD6ar5LQrcLI8kYP9zfGWA9ZH9ePzR/a++JW
ufFb9pT4g63r9z59zHq9xYQIudkFvBI0UUaDsAqj6kknkmgDx2iiigAooooAK9v/AGH/APk7z4Rf
9jHaf+hivEK9v/Yf/wCTvPhF/wBjHaf+higD9yP2nPhj4P8A2nvBniT4NatewweJJNMj1qwaRf3l
o/mSRw3SeqrIjI4H8MmDjeK/O3/gkT4K1n4cfthfEvwv4gs30/WtI8OXNnd279UkS+tQcHuD1BHB
BBHBru/+Ckvx21v9m/8Abe+E3jvQy0klh4eCXdnu2reWrXcwmgb2ZehOcMFbqor7W+GPgTwV8QPi
ppf7Rngy7jkj8UeE/wCzbkxqB9rUzQSQyPj7skYieJweeFXjZQB+cfhv4D6Z+0D/AMFavHmka7CL
rQdH1S41y+tWXctwkPlBIm/2GlkjDDuuR3zXef8ABSf/AIKC+PvhX8W5vhX8MNUTwvBotrCdU1G3
to3nkmljWRYYy6sERY3jOVAbcSMgDBX9n34iaf4H/wCCvnxW0/UbmK1TxKb3SbdpeA1xugmRQexb
yWUDuWA6kV8//wDBWX4M694D/am1rxhPZTN4a8Wx291ZX4QmLzkgSKWEv03hoi+3+660Aev/ALKv
/BVi0PgzxH4T/aMkuPFVjPEIrS+g02OV7mFwyzW9yi7VZcYw2MkFg2eK/Ofx8NBXxz4h/wCEVeaT
wx/aE50trlCkv2UyN5O8EnDbNueTzmvqL9g/9gO5/a+h8SarrGqah4W8M6YI4bfUoLRZBd3LElo1
3EAhFGWI6Fl9a+a/i14X0nwP8UPFfh3QtSk1nSNI1O4sLbUZVVTcpFIyeZgEgBtuR7EUAcnRRRQA
UUUUAez/ALGMXhyb9qr4Xp4tMA0I65AZvtW3yS4OYg+7jaZfLBzxgmv1a/4KK+Ef2pNa1rQNR+B+
qahH4UtLL/TtP0C9S2vzd+YxMjAlWljKeWAqk4IfK85r8iv2c/gTqf7SXxY0vwBo2rafo+q6lHPJ
bz6mXETGKJpWX5FY52oxHHavr/xx+1F+1D/wTx8c2fw98TeJ9O8d6bDZxXNk2sW0l1BNC2RiO4Ij
nO0gpgsQu3gYoA3fGH7fmu2f7MeufB39oP4b+KLnxpqWnXdimranZJab2IP2a4McirueJih3KOdi
nqc18efse/BVv2gf2jvBPg2SEy6ZcXq3Op8cCzhHmzAntuVSgP8Aeda/X/4J/FDw3/wUs/ZW8TL4
28Gw6LHHPNps/msZYIrhIlkS6t5SAyld4OOowQSQefnr/gjD8Hbfw/4b8efGHWTFbQyZ0WwvLghE
jt4sTXUu5sYQt5I3cY8p80AfcrfF7wf8Q/jR44+AV1BHcT2fhmG7vYNw2yw3BeOaAr22xyWze4n7
Y5/nv+NPwxvvgx8WfFngfUdzXWhajNZ+Ywx5sat+7lA9HQq49mFfsP4H+DHwn8IftZah8dI/2kND
1DW9Su7qS40l9SsRBJDMhRbfcJt21B5e3v8Aulr5m/4LR/BL/hHvid4W+J9jb7bTxFa/2bqDqOBd
24Hlsx9XhIUe0BoA/N2iiigAooooAKKKKACiiigAooooAKKKKACus8NfFvxt4OjEeh+Lda0qEDHk
2t/Kkf8A3wGx+lcnRQB65a/tafF6zQrH471JhjH73y5D+bKaoah+038VtTVlm8f66oYYPkXbQ/8A
oGMV5lRQKyLmra1qOvXRudTv7rUbk9ZruZpXP4sSap0UUDCiiigAooooAKKKKACv1Svv+C1nh7V7
OK11L4IHUYYyGEd1rkcihgMbgGtTzgn86/K2igD9OdY/4LTjS9GurfwR8F9M0G/mXK3F1qnmQq/Y
tDFBGX/77Ffnb8TviV4i+MHjzWfGPivUH1PXtWn8+5uGGB0AVFHRUVQqqo4AUDtXMUUAfXf7Cf7e
Vt+xppPjCzuPBcvis6/PbTB49SFp5PlLIMYMT7s+Z7YxXzD488TDxp458ReIVtzaLq2o3N+LcvvM
Xmys+3dgZxuxnAzisKigAooooAKKKKACu6+BfxLT4N/GLwf44k09tVTQNSh1A2KzeUZwjZ2b9rbc
+uDXC0UAfR/7cX7XUH7YfxB0HxLB4Xk8Krpel/2cbaS+F0ZD5skm/cI0x9/GMHp1r0D9iX/gpFq3
7JfgzVvCWp+GpPGfh+a4F3p8A1D7K9jI2fNCkxvlHO1tvGGDH+I18YUUAel/Gv403PxS+PniL4na
Vbz+Gr3UtUGqWsUdzvls5AVKFZAq5ZSoIIAr7g+E/wDwWW1G28JW3h/4sfD+38bOq+XPq1lPHC1y
o6GS2eMxs3qVZQf7or81KKAP0Q/aC/4K863428C3Xg/4X+D4/h9p91C9rNqclwslykLAgrAiKqwt
gn5ssRn5dpGa/O+iigAooooAKKKKANrwV401v4d+LNK8TeHNRm0nXNLuFubS8gOGjdTx7EHkEHgg
kEEE1+kGh/8ABYDwt448MWmm/GL4Laf4pu7fkzWohuLZ2x95YLhW8snv87f0r8xaKAPv39oL/gq9
qnjn4a3fgD4XeB7X4aeH7y3a0nuYpla4WFvvJAkaIkO4Egn5jhjjaea5q4/4KLWekfsYj4D+E/Ac
2gyyaSNMn15tVEnmeY++8k8kQr/rt0wxv+USdTjn4nooAK+3Pjz/AMFHLP8AaE/ZbsPhb4l8AzP4
gs4LFk8Tf2qG/wBMtwqtceSYf+Wi+apG/jzTzXxHRQAUUUUAFFFFABRRRQB//9k=</Data></Thumbnail></Binary></metadata>
